{
  "version": "6.2.0",
  "flags": {},
  "shapes": [
    {
      "label": "gate",
      "points": [
        [
          198.0103626943005,
          186.76683937823833
        ],
        [
          196.19689119170982,
          210.08290155440415
        ],
        [
          172.88082901554404,
          207.75129533678756
        ],
        [
          173.6580310880829,
          184.43523316062175
        ]
      ],
      "group_id": null,
      "description": "",
      "shape_type": "polygon",
      "flags": {},
      "mask": null
    },
    {
      "label": "gate",
      "points": [
        [
          144.12435233160622,
          187.28497409326425
        ],
        [
          143.34715025906735,
          201.5336787564767
        ],
        [
          134.02072538860102,
          206.19689119170985
        ],
        [
          133.76165803108807,
          189.61658031088083
        ]
      ],
      "group_id": null,
      "description": "",
      "shape_type": "polygon",
      "flags": {},
      "mask": null
    },
    {
      "label": "gate",
      "points": [
        [
          154.22797927461139,
          226.14507772020724
        ],
        [
          200.860103626943,
          238.32124352331607
        ],
        [
          201.11822892133773,
          244.0
        ],
        [
          154.7461139896373,
          243.50259067357513
        ]
      ],
      "group_id": null,
      "description": "",
      "shape_type": "polygon",
      "flags": {},
      "mask": null
    }
  ],
  "imagePath": "img_000280.png",
  "imageData": null,
  "imageHeight": 244,
  "imageWidth": 324
}