{
  "version": "6.2.0",
  "flags": {},
  "shapes": [
    {
      "label": "gate",
      "points": [
        [
          121.84455958549222,
          143.76165803108807
        ],
        [
          120.29015544041451,
          175.62694300518135
        ],
        [
          99.2249984741211,
          175.6687469482422
        ],
        [
          101.3782383419689,
          143.50259067357513
        ]
      ],
      "group_id": null,
      "description": "",
      "shape_type": "polygon",
      "flags": {},
      "mask": null
    },
    {
      "label": "gate",
      "points": [
        [
          227.8125,
          132.13125610351562
        ],
        [
          221.7375030517578,
          220.21875
        ],
        [
          151.875,
          205.03125
        ],
        [
          151.875,
          132.13125610351562
        ]
      ],
      "group_id": null,
      "description": "",
      "shape_type": "polygon",
      "flags": {},
      "mask": null
    },
    {
      "label": "gate",
      "points": [
        [
          3.1917098445595684,
          106.9740932642487
        ],
        [
          24.6943005181347,
          110.860103626943
        ],
        [
          24.17616580310879,
          138.83937823834196
        ],
        [
          3.1917098445595684,
          138.32124352331607
        ]
      ],
      "group_id": null,
      "description": "",
      "shape_type": "polygon",
      "flags": {},
      "mask": null
    }
  ],
  "imagePath": "img_000111.png",
  "imageData": null,
  "imageHeight": 244,
  "imageWidth": 324
}