{
  "version": "6.2.0",
  "flags": {},
  "shapes": [
    {
      "label": "gate",
      "points": [
        [
          100.860103626943,
          60.60103626943005
        ],
        [
          201.11917098445596,
          15.264248704663203
        ],
        [
          191.01554404145077,
          243.76165803108807
        ],
        [
          167.18134715025906,
          243.76165803108807
        ],
        [
          91.01554404145077,
          211.63730569948186
        ]
      ],
      "group_id": null,
      "description": "",
      "shape_type": "polygon",
      "flags": {},
      "mask": null
    }
  ],
  "imagePath": "img_000247.png",
  "imageData": null,
  "imageHeight": 244,
  "imageWidth": 324
}